package_name_cod/__init__.py
package_name_cod/processamento/__init__.py
package_name_cod/processamento/combinacao.py
package_name_cod/processamento/transformacao.py
package_name_cod/utils/__init__.py
package_name_cod/utils/io.py
package_name_cod-0.0.1.dist-info/METADATA
package_name_cod-0.0.1.dist-info/WHEEL
package_name_cod-0.0.1.dist-info/top_level.txt
package_name_cod-0.0.1.dist-info/RECORD
