Metadata-Version: 2.1
Name: package-name-cod
Version: 0.0.1
Summary: Pacote de processamento de imagem.
Home-page: https://github.com/Diego-Rapha/package-template.git
Author: Codrix
Author-email: codrix43@gmail.com
Requires-Python: >=3.8
Requires-Dist: matplotlib
Requires-Dist: numpy
Requires-Dist: scikit-image (>=0.16.1)
